pipeline/__init__.py
pipeline/code/__init__.py
pipeline/code/dintegrate/__init__.py
pipeline/code/dintegrate/data_loader.py
pipeline/code/dintegrate/integrate_config.py
pipeline/code/dintegrate/main.py
pipeline/code/dintegrate/utils.py
pipeline/code/dnn/__init__.py
pipeline/code/dnn/analyzer.py
pipeline/code/dnn/dataloader.py
pipeline/code/dnn/main.py
pipeline/code/dnn/models.py
pipeline/code/dnn/pipeline.py
pipeline/code/dnn/config/__init__.py
pipeline/code/dnn/config/logger.py
pipeline/code/dnn/config/parse.py
pipeline/code/dpreprocess/__init__.py
pipeline/code/dpreprocess/ahba_.py
pipeline/code/dpreprocess/sn_.py
pipeline/code/graph_walk/__init__.py
pipeline/code/graph_walk/run.py
pipeline/code/graph_walk/connectomeembeddings/__init__.py
pipeline/code/graph_walk/connectomeembeddings/connectome_embed_nature.py
pipeline/code/graph_walk/connectomeembeddings/node2vec.py
pipeline/run_pipeline/__init__.py
pipeline/run_pipeline/run_sn.py
transbrain/__init__.py
transbrain/atlas.py
transbrain/base.py
transbrain/config.py
transbrain/surf.py
transbrain/trans.py
transbrain/vis.py
transbrain/.ipynb_checkpoints/__init__-checkpoint.py
transbrain/.ipynb_checkpoints/atlas-checkpoint.py
transbrain/.ipynb_checkpoints/base-checkpoint.py
transbrain/.ipynb_checkpoints/trans-checkpoint.py
transbrain/__pycache__/__init__.cpython-311.pyc
transbrain/__pycache__/__init__.cpython-38.pyc
transbrain/__pycache__/atlas.cpython-311.pyc
transbrain/__pycache__/atlas.cpython-38.pyc
transbrain/__pycache__/base.cpython-311.pyc
transbrain/__pycache__/base.cpython-38.pyc
transbrain/__pycache__/config.cpython-311.pyc
transbrain/__pycache__/config.cpython-38.pyc
transbrain/__pycache__/surf.cpython-38.pyc
transbrain/__pycache__/tb_config.cpython-38.pyc
transbrain/__pycache__/trans.cpython-311.pyc
transbrain/__pycache__/trans.cpython-38.pyc
transbrain/__pycache__/vis.cpython-38.pyc
transbrain/atlas/BNA_subregions.xlsx
transbrain/atlas/aal_atlas.csv
transbrain/atlas/aal_atlas_2mm_symmetry.nii.gz
transbrain-1.8.6.dist-info/LICENSE
transbrain-1.8.6.dist-info/METADATA
transbrain-1.8.6.dist-info/WHEEL
transbrain-1.8.6.dist-info/top_level.txt
transbrain-1.8.6.dist-info/RECORD
