Metadata-Version: 2.1
Name: transbrain
Version: 1.8.6
Summary: TransBrain is an integrated computational framework for bidirectional translation of brain-wide phenotypes between humans and mice.
Home-page: https://github.com/ibpshangzheng/transbrain
Author: Shangzheng Huang
Author-email: huangshangzheng@ibp.ac.cn
Classifier: Programming Language :: Python :: 3
Classifier: License :: OSI Approved :: Apache Software License
Classifier: Operating System :: OS Independent
Requires-Python: >=3.8.0,<3.12
License-File: LICENSE
Requires-Dist: matplotlib==3.7.5
Requires-Dist: matplotlib-inline==0.1.7
Requires-Dist: nibabel==5.2.1
Requires-Dist: nilearn==0.10.4
Requires-Dist: numpy==1.24.4
Requires-Dist: openpyxl==3.1.5
Requires-Dist: pandas==2.0.3
Requires-Dist: scikit-learn==1.3.2
Requires-Dist: scipy==1.10.1
Requires-Dist: seaborn==0.13.2
Requires-Dist: six==1.17.0
Requires-Dist: tqdm==4.67.1
Requires-Dist: ipykernel==6.29.5
